mootler/__init__.py
mootler/src/__init__.py
mootler/src/course_data.py
mootler-0.1.data/scripts/moot
mootler-0.1.dist-info/LICENSE
mootler-0.1.dist-info/METADATA
mootler-0.1.dist-info/WHEEL
mootler-0.1.dist-info/top_level.txt
mootler-0.1.dist-info/RECORD
