Metadata-Version: 2.1
Name: mootler
Version: 0.1
Summary: Utility to analyse Moodle data and plot it
Home-page: UNKNOWN
Author: Miguel Rivera
Author-email: miguel.rivera@ucl.ac.uk
License: MIT
Platform: UNKNOWN
Requires-Dist: pandas
Requires-Dist: plotly
